ebi_oct/__init__.py
ebi_oct/napari_plugin/__init__.py
ebi_oct/napari_plugin/napari.yaml
ebi_oct/napari_plugin/widgets.py
ebi_oct/octools/__init__.py
ebi_oct/octools/processing_functions.py
ebi_oct-1.1.0.dist-info/METADATA
ebi_oct-1.1.0.dist-info/WHEEL
ebi_oct-1.1.0.dist-info/entry_points.txt
ebi_oct-1.1.0.dist-info/licenses/LICENSE
ebi_oct-1.1.0.dist-info/RECORD
