Metadata-Version: 2.4
Name: ebi_oct
Version: 1.1.0
Summary: A package for analyzing optical coherence tomography (OCT) images for biofilm.
Author-email: Andreas Netsch <andreas.netsch@partner.kit.edu>, Jonas Ullmann <ullmann@dvgw-ebi.de>
License: MIT
License-File: LICENSE
Classifier: Framework :: napari
Requires-Python: >=3.11
Requires-Dist: customtkinter>=5.2.0
Requires-Dist: magicgui>=0.9.2
Requires-Dist: matplotlib>=3.4.0
Requires-Dist: napari>=0.6.1
Requires-Dist: nibabel>=5.3.2
Requires-Dist: numpy>=1.20.0
Requires-Dist: opencv-python>=4.5.0
Requires-Dist: pyqt6>=6.9.1
Requires-Dist: qtpy>=2.4.0
Requires-Dist: scikit-image>=0.21.0
Requires-Dist: scipy>=1.13.0
Requires-Dist: tifffile>=2020.6.3
Provides-Extra: dev
Requires-Dist: pre-commit==4.2.0; extra == 'dev'
Requires-Dist: pytest==8.4.0; extra == 'dev'
Requires-Dist: ruff==0.12.0; extra == 'dev'
Requires-Dist: sphinx-autodoc-typehints==3.2.0; extra == 'dev'
Requires-Dist: sphinx-rtd-theme==3.0.2; extra == 'dev'
Requires-Dist: sphinx==8.2.3; extra == 'dev'
Requires-Dist: uv==0.6.0; extra == 'dev'
